{"0": [{"part": 0, "min_x": -10.0, "max_x": 9.0, "min_y": -15.5, "max_y": 7.5, "width": 19.0, "height": 23.0}], "1": [{"part": 0, "min_x": -12.0, "max_x": 13.0, "min_y": -14.0, "max_y": 7.0, "width": 25.0, "height": 21.0}], "2": [{"part": 0, "min_x": -19.5, "max_x": 20.5, "min_y": -11.0, "max_y": 5.5, "width": 40.0, "height": 16.5}], "3": [{"part": 0, "min_x": -24.5, "max_x": 23.0, "min_y": -11.5, "max_y": 10.0, "width": 47.5, "height": 21.5}], "4": [{"part": 0, "min_x": -15.0, "max_x": 13.5, "min_y": -12.0, "max_y": 13.5, "width": 28.5, "height": 25.5}], "5": [{"part": 0, "min_x": -15.0, "max_x": 18.0, "min_y": -11.5, "max_y": 13.5, "width": 33.0, "height": 25.0}], "6": [{"part": 0, "min_x": -21.0, "max_x": 22.0, "min_y": -10.0, "max_y": 12.0, "width": 43.0, "height": 22.0}], "7": [{"part": 0, "min_x": -24.5, "max_x": 24.0, "min_y": -10.5, "max_y": 6.5, "width": 48.5, "height": 17.0}], "8": [{"part": 0, "min_x": -10.0, "max_x": 9.5, "min_y": -18.0, "max_y": 7.5, "width": 19.5, "height": 25.5}], "9": [{"part": 0, "min_x": -12.0, "max_x": 13.5, "min_y": -16.5, "max_y": 6.5, "width": 25.5, "height": 23.0}], "10": [{"part": 0, "min_x": -18.5, "max_x": 22.5, "min_y": -15.0, "max_y": 5.0, "width": 41.0, "height": 20.0}], "11": [{"part": 0, "min_x": -19.5, "max_x": 27.0, "min_y": -13.0, "max_y": 15.5, "width": 46.5, "height": 28.5}], "12": [{"part": 0, "min_x": -13.5, "max_x": 12.5, "min_y": -13.5, "max_y": 16.0, "width": 26.0, "height": 29.5}], "13": [{"part": 0, "min_x": -14.0, "max_x": 19.0, "min_y": -13.0, "max_y": 15.5, "width": 33.0, "height": 28.5}], "14": [{"part": 0, "min_x": -18.5, "max_x": 22.5, "min_y": -11.5, "max_y": 17.0, "width": 41.0, "height": 28.5}], "15": [{"part": 0, "min_x": -20.0, "max_x": 25.5, "min_y": -15.5, "max_y": 6.5, "width": 45.5, "height": 22.0}], "16": [{"part": 0, "min_x": -10.5, "max_x": 10.0, "min_y": -20.5, "max_y": 6.5, "width": 20.5, "height": 27.0}], "17": [{"part": 0, "min_x": -10.5, "max_x": 12.5, "min_y": -20.5, "max_y": 5.5, "width": 23.0, "height": 26.0}], "18": [{"part": 0, "min_x": -14.5, "max_x": 21.5, "min_y": -19.5, "max_y": 7.0, "width": 36.0, "height": 26.5}], "19": [{"part": 0, "min_x": -14.5, "max_x": 27.0, "min_y": -14.5, "max_y": 19.0, "width": 41.5, "height": 33.5}], "20": [{"part": 0, "min_x": -11.5, "max_x": 12.5, "min_y": -15.5, "max_y": 16.5, "width": 24.0, "height": 32.0}], "21": [{"part": 0, "min_x": -12.0, "max_x": 18.5, "min_y": -14.5, "max_y": 16.5, "width": 30.5, "height": 31.0}], "22": [{"part": 0, "min_x": -14.0, "max_x": 20.0, "min_y": -14.5, "max_y": 20.5, "width": 34.0, "height": 35.0}], "23": [{"part": 0, "min_x": -16.0, "max_x": 22.5, "min_y": -19.5, "max_y": 8.5, "width": 38.5, "height": 28.0}], "24": [{"part": 0, "min_x": -10.5, "max_x": 12.0, "min_y": -22.0, "max_y": 5.0, "width": 22.5, "height": 27.0}], "25": [{"part": 0, "min_x": -10.5, "max_x": 12.0, "min_y": -23.5, "max_y": 4.5, "width": 22.5, "height": 28.0}], "26": [{"part": 0, "min_x": -10.5, "max_x": 17.0, "min_y": -25.0, "max_y": 7.0, "width": 27.5, "height": 32.0}], "27": [{"part": 0, "min_x": -10.5, "max_x": 23.0, "min_y": -19.0, "max_y": 20.0, "width": 33.5, "height": 39.0}], "28": [{"part": 0, "min_x": -10.0, "max_x": 11.5, "min_y": -17.0, "max_y": 16.0, "width": 21.5, "height": 33.0}], "29": [{"part": 0, "min_x": -10.0, "max_x": 15.5, "min_y": -16.0, "max_y": 16.0, "width": 25.5, "height": 32.0}], "30": [{"part": 0, "min_x": -10.5, "max_x": 14.5, "min_y": -17.0, "max_y": 21.5, "width": 25.0, "height": 38.5}], "31": [{"part": 0, "min_x": -10.5, "max_x": 16.5, "min_y": -25.5, "max_y": 10.5, "width": 27.0, "height": 36.0}], "32": [{"part": 0, "min_x": -11.0, "max_x": 12.5, "min_y": -22.0, "max_y": 4.5, "width": 23.5, "height": 26.5}], "33": [{"part": 0, "min_x": -11.0, "max_x": 12.5, "min_y": -25.5, "max_y": 4.0, "width": 23.5, "height": 29.5}], "34": [{"part": 0, "min_x": -11.0, "max_x": 12.5, "min_y": -29.5, "max_y": 6.0, "width": 23.5, "height": 35.5}], "35": [{"part": 0, "min_x": -11.0, "max_x": 15.5, "min_y": -22.5, "max_y": 17.5, "width": 26.5, "height": 40.0}], "36": [{"part": 0, "min_x": -11.0, "max_x": 12.0, "min_y": -18.0, "max_y": 14.5, "width": 23.0, "height": 32.5}], "37": [{"part": 0, "min_x": -10.5, "max_x": 12.0, "min_y": -17.5, "max_y": 15.0, "width": 22.5, "height": 32.5}], "38": [{"part": 0, "min_x": -11.0, "max_x": 12.0, "min_y": -18.0, "max_y": 20.0, "width": 23.0, "height": 38.0}], "39": [{"part": 0, "min_x": -11.0, "max_x": 12.0, "min_y": -29.5, "max_y": 9.5, "width": 23.0, "height": 39.0}], "40": [{"part": 0, "min_x": -10.5, "max_x": 12.0, "min_y": -21.5, "max_y": 5.5, "width": 22.5, "height": 27.0}], "41": [{"part": 0, "min_x": -10.5, "max_x": 12.0, "min_y": -26.0, "max_y": 5.0, "width": 22.5, "height": 31.0}], "42": [{"part": 0, "min_x": -10.5, "max_x": 16.0, "min_y": -31.0, "max_y": 5.0, "width": 26.5, "height": 36.0}], "43": [{"part": 0, "min_x": -10.5, "max_x": 21.0, "min_y": -25.5, "max_y": 13.0, "width": 31.5, "height": 38.5}], "44": [{"part": 0, "min_x": -10.5, "max_x": 12.5, "min_y": -19.0, "max_y": 12.5, "width": 23.0, "height": 31.5}], "45": [{"part": 0, "min_x": -10.5, "max_x": 12.5, "min_y": -18.5, "max_y": 13.5, "width": 23.0, "height": 32.0}], "46": [{"part": 0, "min_x": -11.5, "max_x": 16.0, "min_y": -18.5, "max_y": 16.0, "width": 27.5, "height": 34.5}], "47": [{"part": 0, "min_x": -11.0, "max_x": 16.5, "min_y": -30.5, "max_y": 7.0, "width": 27.5, "height": 37.5}], "48": [{"part": 0, "min_x": -11.5, "max_x": 10.5, "min_y": -20.0, "max_y": 7.5, "width": 22.0, "height": 27.5}], "49": [{"part": 0, "min_x": -13.0, "max_x": 13.0, "min_y": -25.0, "max_y": 7.0, "width": 26.0, "height": 32.0}], "50": [{"part": 0, "min_x": -14.5, "max_x": 19.5, "min_y": -30.0, "max_y": 6.0, "width": 34.0, "height": 36.0}], "51": [{"part": 0, "min_x": -13.5, "max_x": 25.5, "min_y": -25.5, "max_y": 8.5, "width": 39.0, "height": 34.0}], "52": [{"part": 0, "min_x": -11.5, "max_x": 13.5, "min_y": -19.0, "max_y": 9.5, "width": 25.0, "height": 28.5}], "53": [{"part": 0, "min_x": -14.0, "max_x": 13.0, "min_y": -18.5, "max_y": 11.0, "width": 27.0, "height": 29.5}], "54": [{"part": 0, "min_x": -16.5, "max_x": 20.0, "min_y": -17.5, "max_y": 12.0, "width": 36.5, "height": 29.5}], "55": [{"part": 0, "min_x": -15.5, "max_x": 22.5, "min_y": -28.0, "max_y": 7.5, "width": 38.0, "height": 35.5}], "56": [{"part": 0, "min_x": -11.5, "max_x": 10.0, "min_y": -18.0, "max_y": 9.0, "width": 21.5, "height": 27.0}], "57": [{"part": 0, "min_x": -14.5, "max_x": 12.5, "min_y": -22.0, "max_y": 8.5, "width": 27.0, "height": 30.5}], "58": [{"part": 0, "min_x": -18.5, "max_x": 20.5, "min_y": -26.5, "max_y": 7.5, "width": 39.0, "height": 34.0}], "59": [{"part": 0, "min_x": -18.5, "max_x": 26.5, "min_y": -22.5, "max_y": 6.0, "width": 45.0, "height": 28.5}], "60": [{"part": 0, "min_x": -14.0, "max_x": 14.0, "min_y": -18.5, "max_y": 6.5, "width": 28.0, "height": 25.0}], "61": [{"part": 0, "min_x": -17.5, "max_x": 14.0, "min_y": -18.0, "max_y": 7.0, "width": 31.5, "height": 25.0}], "62": [{"part": 0, "min_x": -19.5, "max_x": 21.0, "min_y": -17.0, "max_y": 7.5, "width": 40.5, "height": 24.5}], "63": [{"part": 0, "min_x": -20.5, "max_x": 25.0, "min_y": -23.5, "max_y": 8.5, "width": 45.5, "height": 32.0}], "64": [{"part": 0, "min_x": -10.0, "max_x": 9.0, "min_y": -17.5, "max_y": 9.0, "width": 19.0, "height": 26.5}], "65": [{"part": 0, "min_x": -14.0, "max_x": 11.0, "min_y": -20.5, "max_y": 8.5, "width": 25.0, "height": 29.0}], "66": [{"part": 0, "min_x": -21.5, "max_x": 18.5, "min_y": -21.0, "max_y": 7.5, "width": 40.0, "height": 28.5}], "67": [{"part": 0, "min_x": -24.0, "max_x": 23.5, "min_y": -17.5, "max_y": 6.5, "width": 47.5, "height": 24.0}], "68": [{"part": 0, "min_x": -14.5, "max_x": 14.0, "min_y": -18.0, "max_y": 6.0, "width": 28.5, "height": 24.0}], "69": [{"part": 0, "min_x": -19.0, "max_x": 14.0, "min_y": -17.5, "max_y": 6.5, "width": 33.0, "height": 24.0}], "70": [{"part": 0, "min_x": -23.0, "max_x": 20.0, "min_y": -16.5, "max_y": 7.5, "width": 43.0, "height": 24.0}], "71": [{"part": 0, "min_x": -25.0, "max_x": 23.5, "min_y": -17.5, "max_y": 8.5, "width": 48.5, "height": 26.0}], "72": [{"part": 0, "min_x": -24.0, "max_x": 31.0, "min_y": -32.0, "max_y": 26.0, "width": 55.0, "height": 58.0}], "73": [{"part": 0, "min_x": -21.0, "max_x": 24.0, "min_y": -32.0, "max_y": 29.0, "width": 45.0, "height": 61.0}], "74": [{"part": 0, "min_x": -31.0, "max_x": 25.0, "min_y": -33.0, "max_y": 24.0, "width": 56.0, "height": 57.0}], "75": [{"part": 0, "min_x": -25.0, "max_x": 21.0, "min_y": -33.0, "max_y": 28.0, "width": 46.0, "height": 61.0}], "76": [{"part": 0, "min_x": -33.0, "max_x": 25.0, "min_y": -39.0, "max_y": 22.0, "width": 58.0, "height": 61.0}], "77": [{"part": 0, "min_x": -27.0, "max_x": 30.0, "min_y": -38.0, "max_y": 24.0, "width": 57.0, "height": 62.0}], "78": [{"part": 0, "min_x": -32.0, "max_x": 25.0, "min_y": -42.0, "max_y": 17.0, "width": 57.0, "height": 59.0}], "79": [{"part": 0, "min_x": -26.0, "max_x": 35.0, "min_y": -39.0, "max_y": 19.0, "width": 61.0, "height": 58.0}], "80": [{"part": 0, "min_x": -25.0, "max_x": 27.0, "min_y": -41.0, "max_y": 16.0, "width": 52.0, "height": 57.0}], "81": [{"part": 0, "min_x": -21.0, "max_x": 35.0, "min_y": -38.0, "max_y": 16.0, "width": 56.0, "height": 54.0}], "82": [{"part": 0, "min_x": -23.0, "max_x": 25.0, "min_y": -37.0, "max_y": 18.0, "width": 48.0, "height": 55.0}], "83": [{"part": 0, "min_x": -20.0, "max_x": 35.0, "min_y": -34.0, "max_y": 18.0, "width": 55.0, "height": 52.0}], "84": [{"part": 0, "min_x": -31.0, "max_x": 22.0, "min_y": -30.0, "max_y": 20.0, "width": 53.0, "height": 50.0}], "85": [{"part": 0, "min_x": -25.0, "max_x": 30.0, "min_y": -32.0, "max_y": 19.0, "width": 55.0, "height": 51.0}], "86": [{"part": 0, "min_x": -34.0, "max_x": 20.0, "min_y": -30.0, "max_y": 20.0, "width": 54.0, "height": 50.0}], "87": [{"part": 0, "min_x": -27.0, "max_x": 21.0, "min_y": -36.0, "max_y": 18.0, "width": 48.0, "height": 54.0}], "88": [{"part": 0, "min_x": -33.0, "max_x": 22.0, "min_y": -28.0, "max_y": 16.0, "width": 55.0, "height": 44.0}], "89": [{"part": 0, "min_x": -26.0, "max_x": 19.0, "min_y": -36.0, "max_y": 14.0, "width": 45.0, "height": 50.0}]}